client/__init__.py
client/client.py
client/client_config.yaml.example
client/control_bus.py
client/dashboard.py
client/database.py
client/models.py
client/tunnel_client.py
client/utils.py
client/static/index.html
client/static/js/api.js
client/static/js/codegen.js
client/static/js/main.js
client/static/js/ui.js
client/static/js/utils.js
shared/__init__.py
shared/protocol.py
tunnel_client-25.11.14.1.dist-info/METADATA
tunnel_client-25.11.14.1.dist-info/WHEEL
tunnel_client-25.11.14.1.dist-info/entry_points.txt
tunnel_client-25.11.14.1.dist-info/top_level.txt
tunnel_client-25.11.14.1.dist-info/RECORD
