Metadata-Version: 2.4
Name: tunnel-client
Version: 25.11.14.1
Summary: Tunnel client for tunnel.tunneloon.online
Requires-Python: >=3.10
Requires-Dist: click>=8.0.0
Requires-Dist: rich>=13.0.0
Requires-Dist: websockets>=12.0
Requires-Dist: httpx>=0.25.0
Requires-Dist: fastapi>=0.104.0
Requires-Dist: uvicorn>=0.24.0
Requires-Dist: sqlalchemy>=2.0.0
Requires-Dist: aiosqlite>=0.19.0
Requires-Dist: pyyaml>=6.0
Dynamic: requires-dist
Dynamic: requires-python
Dynamic: summary
